[
    {
        "gas_name": [
            {
                "name": "CH4",
                "c": "1",
                "h": "4",
                "o": "0",
                "n": "0",
                "s": "0"
            },
            {
                "name": "H2",
                "c": "0",
                "h": "2",
                "o": "0",
                "n": "0",
                "s": "0"
            },
            {
                "name": "O2",
                "c": "0",
                "h": "0",
                "o": "2",
                "n": "0",
                "s": "0"
            },
            {
                "name": "N2",
                "c": "0",
                "h": "0",
                "o": "0",
                "n": "2",
                "s": "0"
            },
            {
                "name": "H2S",
                "c": "0",
                "h": "2",
                "o": "0",
                "n": "0",
                "s": "1"
            },
            {
                "name": "",
                "c": "0",
                "h": "0",
                "o": "0",
                "n": "0",
                "s": "0"
            },
            {
                "name": "",
                "c": "0",
                "h": "0",
                "o": "0",
                "n": "0",
                "s": "0"
            }
        ]
    }
]